dashboard_client.cpython-311-darwin.so
librtde.1.5.7.dylib
librtde.1.5.dylib
librtde.dylib
rtde_control.cpython-311-darwin.so
rtde_io.cpython-311-darwin.so
rtde_receive.cpython-311-darwin.so
script_client.cpython-311-darwin.so
rtde_ur-1.5.7.dist-info/LICENSE
rtde_ur-1.5.7.dist-info/METADATA
rtde_ur-1.5.7.dist-info/WHEEL
rtde_ur-1.5.7.dist-info/top_level.txt
rtde_ur-1.5.7.dist-info/RECORD
