Metadata-Version: 2.1
Name: rtde-ur
Version: 1.5.7
Summary: Forked from ur-rtde. A Python interface for controlling and receiving data from a UR robot using the Real-Time Data Exchange (RTDE) interface of the robot. 
Author: Kenneth Cassel
Author-email: kenneth@reasonrobotics.ai
Classifier: Programming Language :: Python :: 3
Classifier: Programming Language :: Python :: 3.11
Classifier: License :: OSI Approved :: MIT License
Classifier: Operating System :: OS Independent
License-File: LICENSE
